[
    {
        "name": "Civilian",
        "movementType": "Land"
    },
    {
        "name": "Sword",
        "movementType": "Land"
    },
    {
        "name": "Archery",
        "movementType": "Land"
    },
    {
        "name": "Winged",
        "movementType": "Land",
        "uniques": [
            "Can pass through impassable tiles",
			"All tiles cost 1 movement",
            "May travel on Water tiles without embarking",
			"No defensive terrain bonus",
			"Ignores Zone of Control",
			"Eliminates combat penalty for attacking across a coast",
			"Eliminates combat penalty for attacking over a river"
        ]
    },
    {
        "name": "Mage",
        "movementType": "Land",
        "uniques": [
            "Can pass through impassable tiles",
			"Ignores terrain cost",
            "May travel on Water tiles without embarking",
			"Ignores Zone of Control",
			"Eliminates combat penalty for attacking across a coast",
			"Eliminates combat penalty for attacking over a river"
        ]
    },
    {
        "name": "Melee Water",
        "movementType": "Water"
    },
    {
        "name": "Ranged Water",
        "movementType": "Water"
    },
    {
        "name": "Spell",
        "movementType": "Air",
        "uniques": ["Self-destructs when attacking"]
    },
    {
        "name": "Cantrip",
        "movementType": "Air",
        "uniques": ["Self-destructs when attacking"]
    },
    {
        "name": "Spirit",
        "movementType": "Air",
        "uniques": [
            "[+4] Sight",
            "Can see over obstacles",
            "Can perform Air Sweep"
        ]
    }
]